kodosumi/__init__.py
kodosumi/cli.py
kodosumi/config.py
kodosumi/const.py
kodosumi/core.py
kodosumi/dtypes.py
kodosumi/error.py
kodosumi/helper.py
kodosumi/log.py
kodosumi/ops.py
kodosumi/response.py
kodosumi/serve.py
kodosumi/spooler.py
kodosumi/runner/__init__.py
kodosumi/runner/files.py
kodosumi/runner/formatter.py
kodosumi/runner/main.py
kodosumi/runner/tracer.py
kodosumi/service/__init__.py
kodosumi/service/app.py
kodosumi/service/auth.py
kodosumi/service/deploy.py
kodosumi/service/endpoint.py
kodosumi/service/files.py
kodosumi/service/flow.py
kodosumi/service/health.py
kodosumi/service/jwt.py
kodosumi/service/proxy.py
kodosumi/service/role.py
kodosumi/service/server.py
kodosumi/service/store.py
kodosumi/service/admin/__init__.py
kodosumi/service/admin/panel.py
kodosumi/service/admin/static/beer.min.css
kodosumi/service/admin/static/beer.min.js
kodosumi/service/admin/static/black-word.png
kodosumi/service/admin/static/d3.v7.min.js
kodosumi/service/admin/static/favicon.ico
kodosumi/service/admin/static/kodosumi.css
kodosumi/service/admin/static/logo.avif
kodosumi/service/admin/static/logo.png
kodosumi/service/admin/static/material-dynamic-colors.min.js
kodosumi/service/admin/static/material-symbols-outlined.woff2
kodosumi/service/admin/static/white-word.png
kodosumi/service/admin/templates/_eof.html
kodosumi/service/admin/templates/_frame.css
kodosumi/service/admin/templates/_frame.html
kodosumi/service/admin/templates/_kill.html
kodosumi/service/admin/templates/_kill.js
kodosumi/service/admin/templates/_master.html
kodosumi/service/admin/templates/_nav.html
kodosumi/service/admin/templates/_search.html
kodosumi/service/admin/templates/_search.js
kodosumi/service/admin/templates/final.html
kodosumi/service/admin/templates/flow.html
kodosumi/service/admin/templates/form.html
kodosumi/service/admin/templates/form.js
kodosumi/service/admin/templates/login.html
kodosumi/service/admin/templates/routes.html
kodosumi/service/admin/templates/status/_act.js
kodosumi-1.0.3.dist-info/licenses/LICENSE.txt
kodosumi-1.0.3.dist-info/METADATA
kodosumi-1.0.3.dist-info/WHEEL
kodosumi-1.0.3.dist-info/entry_points.txt
kodosumi-1.0.3.dist-info/top_level.txt
kodosumi-1.0.3.dist-info/RECORD
