Metadata-Version: 2.4
Name: kodosumi
Version: 1.0.3
Summary: kodosumi framework to execute and orchestrate agentic services safe and at scale
Author-email: Michael Rau <m.rau@house-of-communication.com>
License-Expression: Apache-2.0
Project-URL: Homepage, https://www.kodosumi.io/
Project-URL: Repository, https://github.com/masumi-network/kodosumi
Project-URL: Issues, https://github.com/masumi-network/kodosumi/issues
Classifier: Programming Language :: Python :: 3.10
Classifier: Operating System :: OS Independent
Classifier: Development Status :: 3 - Alpha
Classifier: Intended Audience :: Developers
Classifier: Intended Audience :: Science/Research
Classifier: Topic :: Scientific/Engineering :: Artificial Intelligence
Requires-Python: >=3.10
License-File: LICENSE.txt
Requires-Dist: click
Requires-Dist: pydantic[email]
Requires-Dist: pydantic_settings
Requires-Dist: ray[serve]
Requires-Dist: litestar
Requires-Dist: fastapi
Requires-Dist: fastapi_utils
Requires-Dist: jinja2
Requires-Dist: uvicorn
Requires-Dist: python-jose
Requires-Dist: python-multipart
Requires-Dist: multipart
Requires-Dist: aiofiles
Requires-Dist: bson
Requires-Dist: bcrypt
Requires-Dist: sqlalchemy
Requires-Dist: advanced-alchemy
Requires-Dist: aiosqlite
Requires-Dist: bs4
Requires-Dist: ansi2html
Requires-Dist: pyyaml
Requires-Dist: markdown
Provides-Extra: tests
Requires-Dist: pytest; extra == "tests"
Requires-Dist: pytest-asyncio; extra == "tests"
Requires-Dist: pytest-httpserver; extra == "tests"
Requires-Dist: isort; extra == "tests"
Requires-Dist: autopep8; extra == "tests"
Requires-Dist: debugpy; extra == "tests"
Requires-Dist: pytest_httpserver; extra == "tests"
Requires-Dist: toml; extra == "tests"
Requires-Dist: build; extra == "tests"
Requires-Dist: twine; extra == "tests"
Dynamic: license-file
